brat/.htaccess
brat/CONTRIBUTING.md
brat/CONTRIBUTORS.md
brat/LICENSE.md
brat/README.md
brat/ajax.cgi
brat/ajax.fcgi
brat/apache-group.sh
brat/apache-user.sh
brat/config_template.py
brat/diff.xhtml
brat/favicon.ico
brat/index.html
brat/index.xhtml
brat/lighttpd_fcgi.conf
brat/offline.xhtml
brat/standalone.py
brat/testserver.py
brat/tutorial.cgi
brat/client/lib/head.load.min.js
brat/client/lib/jquery-ui-1.8.16.custom.min.js
brat/client/lib/jquery-ui.combobox.js
brat/client/lib/jquery-ui.min.js
brat/client/lib/jquery.ba-bbq.min.js
brat/client/lib/jquery.json.min.js
brat/client/lib/jquery.min.js
brat/client/lib/jquery.svg.min.js
brat/client/lib/jquery.svgdom.min.js
brat/client/lib/sprintf.js
brat/client/lib/webfont.js
brat/client/src/ajax.js
brat/client/src/annotation_log.js
brat/client/src/annotator_ui.js
brat/client/src/configuration.js
brat/client/src/dispatcher.js
brat/client/src/offline_ajax.js
brat/client/src/spinner.js
brat/client/src/url_monitor.js
brat/client/src/util.js
brat/client/src/visualizer.js
brat/client/src/visualizer_ui.js
brat/configurations/acl.conf
brat/configurations/AnEM/annotation.conf
brat/configurations/AnEM/visual.conf
brat/configurations/AnatEM/annotation.conf
brat/configurations/AnatEM/visual.conf
brat/configurations/BioNLP-ST-2013-CG/annotation.conf
brat/configurations/BioNLP-ST-2013-CG/kb_shortcuts.conf
brat/configurations/BioNLP-ST-2013-CG/visual.conf
brat/configurations/BioNLP-ST-2013-PC/annotation.conf
brat/configurations/BioNLP-ST-2013-PC/visual.conf
brat/configurations/BioNLP-ST-CO/annotation.conf
brat/configurations/BioNLP-ST-CO/visual.conf
brat/configurations/BioNLP-ST-EPI/annotation.conf
brat/configurations/BioNLP-ST-EPI/visual.conf
brat/configurations/BioNLP-ST-GE/annotation.conf
brat/configurations/BioNLP-ST-GE/visual.conf
brat/configurations/BioNLP-ST-ID/annotation.conf
brat/configurations/BioNLP-ST-ID/visual.conf
brat/configurations/BioNLP-ST-REL/annotation.conf
brat/configurations/BioNLP-ST-REL/visual.conf
bratserver-0.0.1.dist-info/METADATA
bratserver-0.0.1.dist-info/WHEEL
bratserver-0.0.1.dist-info/entry_points.txt
bratserver-0.0.1.dist-info/top_level.txt
bratserver-0.0.1.dist-info/RECORD
