Metadata-Version: 2.1
Name: bratserver
Version: 0.0.1
Summary: BRAT (brat rapid annotation tool) is based on the stav visualiser,
Author-email: Sampo Pyysalo <sampo.pyysalo@utu.fi>
License: # Licenses #
Project-URL: Homepage, https://github.com/nlplab/brat
Keywords: brat rapid annotation tool 
Classifier: Intended Audience :: Developers
Classifier: Natural Language :: English
Classifier: License :: OSI Approved :: MIT License
Classifier: Programming Language :: Python :: 3
Classifier: Programming Language :: Python :: 3.8
Classifier: Programming Language :: Python :: 3.9
Classifier: Programming Language :: Python :: 3.10
Requires-Python: >=3.8
Requires-Dist: gunicorn
Provides-Extra: dev
Requires-Dist: black ; extra == 'dev'
Requires-Dist: ruamel.yaml ; extra == 'dev'
Requires-Dist: pytest ; extra == 'dev'
Requires-Dist: pytest-cov ; extra == 'dev'
